tools4vasp/__init__.py
tools4vasp/add_MODECAR.py
tools4vasp/calc_deformation_density.py
tools4vasp/chgcar2cube.py
tools4vasp/elf2cube.py
tools4vasp/freq2jmol.py
tools4vasp/freq2mode.py
tools4vasp/kgrid2kspacing.py
tools4vasp/kspacing2kgrid.py
tools4vasp/mixed_interpolate.py
tools4vasp/neb2movie.py
tools4vasp/plotIRC.py
tools4vasp/plotNEB.py
tools4vasp/plot_neb_movie.py
tools4vasp/poscar2nbands.py
tools4vasp/replace_potcar_symlinks.py
tools4vasp/split_vasp_freq.py
tools4vasp/vasp2traj.py
tools4vasp/vaspGetEF.py
tools4vasp/vaspcheck.py
tools4vasp/viewMode.py
tools4vasp/visualize_magnitization.py
tools4vasp/bash_scripts/__init__.py
tools4vasp-1.0.1.dist-info/licenses/LICENSE
tools4vasp-1.0.1.dist-info/METADATA
tools4vasp-1.0.1.dist-info/WHEEL
tools4vasp-1.0.1.dist-info/entry_points.txt
tools4vasp-1.0.1.dist-info/top_level.txt
tools4vasp-1.0.1.dist-info/RECORD
