Metadata-Version: 2.4
Name: tools4vasp
Version: 1.0.1
Summary: Python tools for VASP
Author-email: Patrick Melix <patrick.melix@uni-leipzig.de>
Project-URL: Homepage, https://github.com/Tonner-Zech-Group/VASP-tools
Project-URL: Issues, https://github.com/Tonner-Zech-Group/VASP-tools/issues
Classifier: Programming Language :: Python :: 3
Classifier: Programming Language :: Unix Shell
Classifier: License :: OSI Approved :: MIT License
Classifier: Operating System :: Unix
Classifier: Intended Audience :: Science/Research
Classifier: Topic :: Scientific/Engineering :: Chemistry
Requires-Python: >=3.8
License-File: LICENSE
Requires-Dist: ase>=1.0
Requires-Dist: matplotlib>=3.8.4
Requires-Dist: natsort>=8.3.1
Requires-Dist: numpy>=1.24.3
Requires-Dist: pymatgen>=2023.5.10
Dynamic: license-file
